glyrics/__init__.py
glyrics/__main__.py
glyrics/app.py
glyrics/config/__init__.py
glyrics/config/config.json
glyrics/config/config.py
glyrics/config/gunicorn.conf.py
glyrics-0.1.0.dist-info/LICENSE
glyrics-0.1.0.dist-info/METADATA
glyrics-0.1.0.dist-info/WHEEL
glyrics-0.1.0.dist-info/entry_points.txt
glyrics-0.1.0.dist-info/RECORD
