Metadata-Version: 2.1
Name: glyrics
Version: 0.1.0
Summary: Flask app for fetching song lyrics from the Genius API
Author: William Dye
Requires-Python: >=3.10,<4.0
Classifier: Programming Language :: Python :: 3
Classifier: Programming Language :: Python :: 3.10
Classifier: Programming Language :: Python :: 3.11
Requires-Dist: flask (>=3.1.2,<4.0.0)
Requires-Dist: lyricsgenius (>=3.7.5,<4.0.0)
